MANIFEST.in
README.md
setup.py
deepchem/__init__.py
deepchem/data/__init__.py
deepchem/data/data_loader.py
deepchem/data/datasets.py
deepchem/data/supports.py
deepchem/dock/__init__.py
deepchem/dock/binding_pocket.py
deepchem/dock/docking.py
deepchem/dock/pose_generation.py
deepchem/dock/pose_scoring.py
deepchem/feat/__init__.py
deepchem/feat/adjacency_fingerprints.py
deepchem/feat/atomic_coordinates.py
deepchem/feat/base_classes.py
deepchem/feat/basic.py
deepchem/feat/binding_pocket_features.py
deepchem/feat/coulomb_matrices.py
deepchem/feat/fingerprints.py
deepchem/feat/graph_features.py
deepchem/feat/materials_featurizers.py
deepchem/feat/mol_graphs.py
deepchem/feat/one_hot.py
deepchem/feat/raw_featurizer.py
deepchem/feat/rdkit_grid_featurizer.py
deepchem/feat/smiles_featurizers.py
deepchem/hyper/__init__.py
deepchem/hyper/base_classes.py
deepchem/hyper/gaussian_process.py
deepchem/hyper/grid_search.py
deepchem/metalearning/__init__.py
deepchem/metalearning/maml.py
deepchem/metrics/__init__.py
deepchem/metrics/genomic_metrics.py
deepchem/models/IRV.py
deepchem/models/__init__.py
deepchem/models/atomic_conv.py
deepchem/models/callbacks.py
deepchem/models/chemnet_layers.py
deepchem/models/chemnet_models.py
deepchem/models/cnn.py
deepchem/models/fcnet.py
deepchem/models/gan.py
deepchem/models/graph_models.py
deepchem/models/keras_model.py
deepchem/models/layers.py
deepchem/models/losses.py
deepchem/models/models.py
deepchem/models/multitask.py
deepchem/models/optimizers.py
deepchem/models/progressive_multitask.py
deepchem/models/robust_multitask.py
deepchem/models/scscore.py
deepchem/models/seqtoseq.py
deepchem/models/text_cnn.py
deepchem/models/sklearn_models/__init__.py
deepchem/models/xgboost_models/__init__.py
deepchem/molnet/__init__.py
deepchem/molnet/check_availability.py
deepchem/molnet/dnasim.py
deepchem/molnet/preset_hyper_parameters.py
deepchem/molnet/run_benchmark.py
deepchem/molnet/run_benchmark_low_data.py
deepchem/molnet/run_benchmark_models.py
deepchem_nightly.egg-info/PKG-INFO
deepchem_nightly.egg-info/SOURCES.txt
deepchem_nightly.egg-info/dependency_links.txt
deepchem_nightly.egg-info/requires.txt
deepchem_nightly.egg-info/top_level.txt